ltws/__init__.py
ltws/cli.py
ltws/exceptions.py
ltws/gui.py
ltws/models.py
ltws/packager.py
ltws/parser.py
ltws/utils.py
ltws/validator.py
ltws/variables.py
ltws_parser-1.5.1.dist-info/METADATA
ltws_parser-1.5.1.dist-info/WHEEL
ltws_parser-1.5.1.dist-info/entry_points.txt
ltws_parser-1.5.1.dist-info/top_level.txt
ltws_parser-1.5.1.dist-info/RECORD
