Metadata-Version: 2.4
Name: ltws-parser
Version: 1.5.1
Summary: LTWS 协议解析器
Author-email: Little Tree Studio <studio@zsxiaoshu.cn>
License: MIT
Project-URL: Homepage, https://github.com/shu-shu-1/ltws-parser
Project-URL: Repository, https://github.com/shu-shu-1/ltws-parser
Project-URL: Bug Tracker, https://github.com/shu-shu-1/ltws-parser/issues
Classifier: Development Status :: 4 - Beta
Classifier: Intended Audience :: Developers
Classifier: License :: OSI Approved :: MIT License
Classifier: Operating System :: OS Independent
Classifier: Programming Language :: Python :: 3
Classifier: Programming Language :: Python :: 3.8
Classifier: Programming Language :: Python :: 3.9
Classifier: Programming Language :: Python :: 3.10
Classifier: Programming Language :: Python :: 3.11
Classifier: Programming Language :: Python :: 3.12
Classifier: Programming Language :: Python :: 3.13
Classifier: Programming Language :: Python :: 3.14
Classifier: Topic :: Software Development :: Libraries :: Python Modules
Classifier: Topic :: Multimedia :: Graphics
Requires-Python: >=3.8
Requires-Dist: rtoml>=0.11.0
Requires-Dist: requests>=2.28.0
Requires-Dist: httpx>=0.24.0
Requires-Dist: pydantic>=2.10.6
Requires-Dist: click>=8.1.8
Provides-Extra: cli
Requires-Dist: click>=8.0.0; extra == "cli"
Requires-Dist: rich>=13.0.0; extra == "cli"
